README.rst
setup.py
TimeWheel.egg-info/PKG-INFO
TimeWheel.egg-info/SOURCES.txt
TimeWheel.egg-info/dependency_links.txt
TimeWheel.egg-info/not-zip-safe
TimeWheel.egg-info/top_level.txt
timeWheel/__init__.py
timeWheel/threadTimeWheel.py
timeWheel/timeCache.py