Metadata-Version: 1.1
Name: TimeWheel
Version: 0.0.3
Summary: Python implementation of time wheel,Task runer,Cache
Home-page: https://www.pkold.com
Author: zhenruyan
Author-email: baiyangwangzhan@hotmail.com
License: WTFPL
Platform: linux
Classifier: Operating System :: OS Independent
Classifier: Intended Audience :: Developers
Classifier: Programming Language :: Python :: 3.7
Classifier: Topic :: Software Development :: Libraries
